README.rst
setup.py
multitomorrow.egg-info/PKG-INFO
multitomorrow.egg-info/SOURCES.txt
multitomorrow.egg-info/dependency_links.txt
multitomorrow.egg-info/requires.txt
multitomorrow.egg-info/top_level.txt
tomorrow/__init__.py
tomorrow/tomorrow.py