Metadata-Version: 1.0
Name: multitomorrow
Version: 0.3.0
Summary: Magic decorator syntax for asynchronous code
Home-page: https://github.com/ResolveWang/Tomorrow
Author: ResolveWang
Author-email: w1796246076@sina.com
License: MIT License (See LICENSE)
Platform: UNKNOWN
